onnxruntime_transformers/OnnxruntimeTransformers.py
onnxruntime_transformers/__init__.py
onnxruntime_transformers-0.1.4.dist-info/licenses/LICENSE
onnxruntime_transformers-0.1.4.dist-info/METADATA
onnxruntime_transformers-0.1.4.dist-info/WHEEL
onnxruntime_transformers-0.1.4.dist-info/pypi-token.txt
onnxruntime_transformers-0.1.4.dist-info/top_level.txt
onnxruntime_transformers-0.1.4.dist-info/RECORD
