Metadata-Version: 2.4
Name: onnxruntime_transformers
Version: 0.1.4
Summary: transformers for production runtime, 3x faster on cpu, no pytorch nor tensorflow included
Home-page: https://github.com/billju/onnxruntime_transformers
Author: chuboy
Author-email: billju666@gmail.com
Classifier: Programming Language :: Python :: 3
Classifier: License :: OSI Approved :: MIT License
Classifier: Operating System :: OS Independent
Requires-Python: >=3.8
License-File: LICENSE
Requires-Dist: tokenizers
Requires-Dist: onnxruntime
Dynamic: author
Dynamic: author-email
Dynamic: classifier
Dynamic: description
Dynamic: description-content-type
Dynamic: home-page
Dynamic: license-file
Dynamic: requires-dist
Dynamic: requires-python
Dynamic: summary
